dotcontrol/__init__.py
dotcontrol/cli.py
dotcontrol/const.py
dotcontrol/control.py
dotcontrol/dot.py
dotcontrol/profile.py
dotcontrol/remote.py
dotcontrol/util.py
dotcontrol-0.0.3.dist-info/LICENSE
dotcontrol-0.0.3.dist-info/METADATA
dotcontrol-0.0.3.dist-info/WHEEL
dotcontrol-0.0.3.dist-info/entry_points.txt
dotcontrol-0.0.3.dist-info/top_level.txt
dotcontrol-0.0.3.dist-info/RECORD
